{
  "task_id": "0024-execute-meeting-rewrites",
  "agent_id": "copilot-cli",
  "status": "done",
  "completed_at": "2026-05-17T11:01:22.859017+00:00",
  "files_changed": [
    "social-plus-sdk/social/posts/viewing-post-content.mdx",
    "social-plus-sdk/social/discovery-engagement/search/intelligent-search-community.mdx",
    "use-cases/social/search-and-discovery.mdx",
    "social-plus-sdk/social/content-management/posts/creation/room-post.mdx",
    "social-plus-sdk/video-new/broadcasting/co-host-management.mdx"
  ],
  "validators_run": [
    "meeting_rewrites_resolved"
  ],
  "notes": "R1 AmityPollRepository\u2192PollRepository (viewing-post-content.mdx): import and \u00d73 body refs renamed. Type annotation updated to typeof PollRepository. new AmityPollRepository(client) \u2192 PollRepository namespace ref with comment. needs_review: block uses class-instantiation pattern incompatible with namespace; functional refactor deferred.\nR2 CommunityRepository.AmityCommunityMemberStatusFilter\u2192AmityCommunityMemberStatusFilter: \u00d71 intelligent-search-community.mdx (L153), \u00d72 search-and-discovery.mdx (L85, L107). AmityCommunityMemberStatusFilter added to import in all 3 blocks.\nR3 InvitationRepository.getMyRoomInvitations\u2192getInvitations({targetType:room, targetId:roomId, limit}): \u00d71 room-post.mdx (L336), \u00d71 co-host-management.mdx (L216). Signature mapped: { limit } \u2192 { targetType: \"room\", targetId: roomId, limit }. Function renamed getMyRoomInvitations\u2192getRoomInvitations(roomId: string). roomId is a placeholder \u2014 caller must supply the actual room ID.\nDrift: 30\u219228 (\u22122)."
}
