{
  "dimension": "completeness",
  "page": "social-plus-sdk/core-concepts/user-management/user-operations/get-user-information.mdx",
  "cohort": "shared",
  "score": 4,
  "rationale": "getUser(), searchUserByDisplayName(), and getUsersByIds() are all shown with code; return types (LiveObject/LiveCollection) and real-time update behavior documented; primary error case (user not found) noted \u2014 missing: searchUserByDisplayName pagination parameters and maximum results.",
  "confidence": "high",
  "suggestions": [
    "Document the pagination parameters for searchUserByDisplayName \u2014 page size, whether cursor-based or offset, and maximum results per query.",
    "Add a note on getUsersByIds() limits \u2014 is there a maximum number of IDs per call?"
  ],
  "_prompt_hash": "d2a048cdebec7018220e89c4189351e59e356dc07fd7bce40d4e2c5e99d393da",
  "_scored_by": "copilot-cli",
  "_scored_at": "2026-05-19T07:30:00Z"
}
